audiodotturn/__init__.py
audiodotturn/adt.py
audiodotturn/run.py
audiodotturn/config/__init__.py
audiodotturn/config/config.ini
audiodotturn/config/config.py
audiodotturn/construct/__init__.py
audiodotturn/construct/construction.py
audiodotturn/database/__init__.py
audiodotturn/database/database.py
audiodotturn/extract/__init__.py
audiodotturn/extract/extraction.py
audiodotturn/parser/__init__.py
audiodotturn/parser/parser.py
audiodotturn-0.5.5.dist-info/LICENSE
audiodotturn-0.5.5.dist-info/METADATA
audiodotturn-0.5.5.dist-info/WHEEL
audiodotturn-0.5.5.dist-info/entry_points.txt
audiodotturn-0.5.5.dist-info/top_level.txt
audiodotturn-0.5.5.dist-info/RECORD
