Metadata-Version: 2.1
Name: audiodotturn
Version: 0.5.5
Summary: A tool/library for formatting and cataloging audio files, mainly for files with no metadata.
Author-email: tairenfd <tairenfd@mailbox.org>
License: MIT License
Project-URL: homepage, https://audiodotturn.tairenfd.xyz
Project-URL: repository, https://github.com/tairenfd/audiodotturn
Keywords: audio,music,organizer,metadata,formatter,tagger,manager,cli
Classifier: Development Status :: 3 - Alpha
Classifier: Intended Audience :: End Users/Desktop
Classifier: License :: OSI Approved :: MIT License
Classifier: Operating System :: POSIX :: Linux
Classifier: Environment :: Console
Classifier: Programming Language :: Python :: 3
Classifier: Topic :: Utilities
Requires-Python: >=3.11
License-File: LICENSE
Requires-Dist: rich
Requires-Dist: pyyaml
